FloorFieldModel/FFM.py
FloorFieldModel/__init__.py
FloorFieldModel/cp/__init__.py
FloorFieldModel/cp/calc_probability.py
FloorFieldModel/dcm/__init__.py
FloorFieldModel/dcm/distance_calc_method.py
FloorFieldModel/examples/__init__.py
FloorFieldModel/examples/test.py
FloorFieldModel/examples/map/__init__.py
FloorFieldModel/examples/map/corner.npy
FloorFieldModel/examples/map/room.npy
FloorFieldModel/hc/__init__.py
FloorFieldModel/hc/handle_collisions.py
FloorFieldModel/sql/__init__.py
FloorFieldModel/sql/create_and_save_sqlite.py
FloorFieldModel-0.1.5.dist-info/LICENSE
FloorFieldModel-0.1.5.dist-info/METADATA
FloorFieldModel-0.1.5.dist-info/WHEEL
FloorFieldModel-0.1.5.dist-info/top_level.txt
FloorFieldModel-0.1.5.dist-info/RECORD
